pepe/__init__.py
pepe/analysis/BrightnessGSquared.py
pepe/analysis/D2Min.py
pepe/analysis/Derivative.py
pepe/analysis/ForceBalance.py
pepe/analysis/ForceSolve.py
pepe/analysis/LinearRegions.py
pepe/analysis/NetworkAnalysis.py
pepe/analysis/__init__.py
pepe/auto/ForceSolve.py
pepe/auto/ParameterSelect.py
pepe/auto/TrialObject.py
pepe/auto/__init__.py
pepe/preprocess/Filter.py
pepe/preprocess/Image.py
pepe/preprocess/Mask.py
pepe/preprocess/Rescale.py
pepe/preprocess/Video.py
pepe/preprocess/__init__.py
pepe/simulate/SyntheticPE.py
pepe/simulate/__init__.py
pepe/test/__init__.py
pepe/test/test_auto.py
pepe/test/test_conv_tracking.py
pepe/test/test_synthetic_force_solve.py
pepe/test/test_utils.py
pepe/topology/Clustering.py
pepe/topology/PersistentHomology.py
pepe/topology/__init__.py
pepe/tracking/AngularConvolution.py
pepe/tracking/CNNDetection.py
pepe/tracking/Convolution.py
pepe/tracking/DTypes.py
pepe/tracking/Hough.py
pepe/tracking/__init__.py
pepe/utils/Coordinates.py
pepe/utils/CourseGrain.py
pepe/utils/FittingFunctions.py
pepe/utils/Kwargs.py
pepe/utils/Outer.py
pepe/utils/Parse.py
pepe/utils/RectArr.py
pepe/utils/Sort.py
pepe/utils/__init__.py
pepe/visualize/Circles.py
pepe/visualize/Colors.py
pepe/visualize/Forces.py
pepe/visualize/Rotation.py
pepe/visualize/__init__.py
pepe_granular-1.2.9.dist-info/LICENSE.md
pepe_granular-1.2.9.dist-info/METADATA
pepe_granular-1.2.9.dist-info/WHEEL
pepe_granular-1.2.9.dist-info/top_level.txt
pepe_granular-1.2.9.dist-info/RECORD
