Metadata-Version: 2.2
Name: pepe-granular
Version: 1.2.9
Summary: Image analysis toolbox tailored towards granular photoelastic images
Home-page: https://jfeatherstone.github.io/pepe/pepe
Author: Jack Featherstone
Author-email: jack.featherstone@oist.jp
License: MIT
Classifier: Programming Language :: Python :: 3.7
Classifier: Programming Language :: Python :: 3.11
Classifier: License :: OSI Approved :: MIT License
Classifier: Operating System :: OS Independent
License-File: LICENSE.md
Dynamic: author
Dynamic: author-email
Dynamic: classifier
Dynamic: description
Dynamic: description-content-type
Dynamic: home-page
Dynamic: license
Dynamic: summary
